{
  "timestamp": "2026-07-01T15:28:00.006Z",
  "coins": {
    "ETH": {
      "price": 1624.2,
      "change": 3.7403,
      "fr": 0.007055,
      "ls": 2.790750568612585,
      "oi": 1145.82697272,
      "oiChg": 2.3462580172226284,
      "longs": 73.61999999999999,
      "shorts": 26.38
    },
    "BNB": {
      "price": 553.5,
      "change": 1.541,
      "fr": 0.0075190000000000005,
      "ls": 2.3636057854019508,
      "oi": 70.81426970999999,
      "oiChg": -0.5119078649826115,
      "longs": 70.27,
      "shorts": 29.73
    },
    "AVAX": {
      "price": 6.73,
      "change": 4.0988999999999995,
      "fr": 0.001343,
      "ls": 2.631082062454612,
      "oi": 35.013245625,
      "oiChg": -0.5438983826825688,
      "longs": 72.46000000000001,
      "shorts": 27.54
    },
    "DOGE": {
      "price": 0.0734,
      "change": 3.8483000000000005,
      "fr": 0.00996,
      "ls": 3.106776180698152,
      "oi": 90.8477244812,
      "oiChg": -0.1039160021358344,
      "longs": 75.64999999999999,
      "shorts": 24.349999999999998
    },
    "NEAR": {
      "price": 1.8512,
      "change": 3.8716,
      "fr": 0.01,
      "ls": 1.5207965717166623,
      "oi": 64.85174063055999,
      "oiChg": -0.08925817145299147,
      "longs": 60.33,
      "shorts": 39.67
    },
    "SUI": {
      "price": 0.7195,
      "change": 4.2149,
      "fr": 0.008101,
      "ls": 3.189359028068705,
      "oi": 54.49904554,
      "oiChg": -0.1541469808730672,
      "longs": 76.13,
      "shorts": 23.87
    },
    "MATIC": {
      "price": 0,
      "change": 0,
      "fr": 0,
      "ls": 1,
      "oi": 0,
      "oiChg": 0,
      "longs": 50,
      "shorts": 50
    },
    "LTC": {
      "price": 42.67,
      "change": 2.3261,
      "fr": 0.01,
      "ls": 3.1254125412541254,
      "oi": 47.30084282299958,
      "oiChg": 0.19604867466486386,
      "longs": 75.76,
      "shorts": 24.240000000000002
    },
    "SOL": {
      "price": 77.67,
      "change": 5.961799999999999,
      "fr": 0.005919,
      "ls": 2.2722513089005236,
      "oi": 631.49616801,
      "oiChg": 1.1094037294451935,
      "longs": 69.44,
      "shorts": 30.56
    },
    "XLM": {
      "price": 0.20196,
      "change": 11.9698,
      "fr": -0.01324,
      "ls": 1.8481913984619767,
      "oi": 30.7505325996,
      "oiChg": 1.0531875802504371,
      "longs": 64.89,
      "shorts": 35.11
    },
    "HYPE": {
      "price": 64.445,
      "change": -0.8385,
      "fr": -0.002463,
      "ls": 1.6490066225165565,
      "oi": 219.58098412319998,
      "oiChg": -0.8688308927623002,
      "longs": 62.25000000000001,
      "shorts": 37.75
    },
    "ATOM": {
      "price": 1.5537,
      "change": 1.8152000000000001,
      "fr": 0.00646,
      "ls": 2.506311360448808,
      "oi": 15.653143425360001,
      "oiChg": 0.28762699437675554,
      "longs": 71.48,
      "shorts": 28.52
    },
    "SHIB": {
      "price": 0,
      "change": 0,
      "fr": 0,
      "ls": 1,
      "oi": 0,
      "oiChg": 0,
      "longs": 50,
      "shorts": 50
    },
    "AAVE": {
      "price": 87.41,
      "change": 2.5818,
      "fr": 0.01,
      "ls": 1.6178010471204187,
      "oi": 44.7979431724,
      "oiChg": 0.6284432354369182,
      "longs": 61.8,
      "shorts": 38.2
    },
    "ADA": {
      "price": 0.1572,
      "change": 9.0152,
      "fr": 0.006748,
      "ls": 2.616636528028933,
      "oi": 48.469262050800005,
      "oiChg": -2.3353097937299525,
      "longs": 72.35000000000001,
      "shorts": 27.650000000000002
    },
    "DOT": {
      "price": 0.8471,
      "change": 3.7222,
      "fr": 0.01,
      "ls": 2.835826620636747,
      "oi": 17.715362740430002,
      "oiChg": -0.09855311923653043,
      "longs": 73.92999999999999,
      "shorts": 26.07
    },
    "BCH": {
      "price": 217.9,
      "change": 9.8286,
      "fr": 0.008878,
      "ls": 2.337783711615488,
      "oi": 29.313191431000007,
      "oiChg": 1.1226209186270744,
      "longs": 70.04,
      "shorts": 29.959999999999997
    },
    "BTC": {
      "price": 60321,
      "change": 3.2718,
      "fr": 0.007732,
      "ls": 1.775464890369137,
      "oi": 3523.115323236,
      "oiChg": -0.363321902017853,
      "longs": 63.970000000000006,
      "shorts": 36.03
    },
    "KAS": {
      "price": 0.03149,
      "change": 2.9084,
      "fr": 0.005,
      "ls": 2.2711808963035653,
      "oi": 6.162536317999999,
      "oiChg": 1.46214675346141,
      "longs": 69.43,
      "shorts": 30.570000000000004
    },
    "WLD": {
      "price": 0.4033,
      "change": -2.4903,
      "fr": 0.0033410000000000002,
      "ls": 2.372681281618887,
      "oi": 46.73745649703999,
      "oiChg": 0.253402126540465,
      "longs": 70.35,
      "shorts": 29.65
    },
    "CRO": {
      "price": 0.05482,
      "change": 2.7939,
      "fr": 0.01,
      "ls": 2.563791874554526,
      "oi": 1.99199434,
      "oiChg": 0.5795955591411177,
      "longs": 71.94,
      "shorts": 28.060000000000002
    },
    "ALGO": {
      "price": 0.0857,
      "change": 3.8158,
      "fr": 0.006483999999999999,
      "ls": 1.8760425654299684,
      "oi": 6.3982884694,
      "oiChg": -0.541086155509116,
      "longs": 65.23,
      "shorts": 34.77
    },
    "ONDO": {
      "price": 0.3201,
      "change": 3.5252,
      "fr": 0.005,
      "ls": 3.5892611289582375,
      "oi": 24.529723943999997,
      "oiChg": 0.857518919017238,
      "longs": 78.21000000000001,
      "shorts": 21.790000000000003
    },
    "PEPE": {
      "price": 0,
      "change": 0,
      "fr": 0,
      "ls": 1,
      "oi": 0,
      "oiChg": 0,
      "longs": 50,
      "shorts": 50
    },
    "LINK": {
      "price": 7.435,
      "change": 3.5803000000000003,
      "fr": 0.000111,
      "ls": 3.045307443365696,
      "oi": 46.677328515999996,
      "oiChg": -0.21897916717858562,
      "longs": 75.28,
      "shorts": 24.72
    },
    "QNT": {
      "price": 67.81,
      "change": 5.738300000000001,
      "fr": 0.01,
      "ls": 0.9712201852946976,
      "oi": 1.8454667806,
      "oiChg": -2.06364308971411,
      "longs": 49.27,
      "shorts": 50.73
    },
    "ENA": {
      "price": 0.07301,
      "change": 3.8253000000000004,
      "fr": 0.004535,
      "ls": 3.460303300624442,
      "oi": 41.26534749708001,
      "oiChg": -0.48237044782444055,
      "longs": 77.58,
      "shorts": 22.42
    },
    "XRP": {
      "price": 1.063,
      "change": 2.9539,
      "fr": -0.007175,
      "ls": 3.9900199600798403,
      "oi": 199.1184125702,
      "oiChg": -5.122890516992818,
      "longs": 79.96,
      "shorts": 20.04
    },
    "BONK": {
      "price": 0,
      "change": 0,
      "fr": 0,
      "ls": 1,
      "oi": 0,
      "oiChg": 0,
      "longs": 50,
      "shorts": 50
    },
    "UNI": {
      "price": 2.813,
      "change": 1.7359,
      "fr": 0.01,
      "ls": 2.294892915980231,
      "oi": 20.1411978647,
      "oiChg": -0.09459423803408411,
      "longs": 69.65,
      "shorts": 30.349999999999998
    },
    "INJ": {
      "price": 4.817,
      "change": 4.7173,
      "fr": 0.006495000000000001,
      "ls": 1.930832356389215,
      "oi": 10.2257756755,
      "oiChg": 0.5759667931116091,
      "longs": 65.88000000000001,
      "shorts": 34.12
    },
    "TRX": {
      "price": 0.31835,
      "change": 0.6067,
      "fr": -0.008977,
      "ls": 1.7578599007170435,
      "oi": 49.308668338850005,
      "oiChg": -0.14403045538059206,
      "longs": 63.739999999999995,
      "shorts": 36.26
    },
    "RENDER": {
      "price": 1.5438,
      "change": 2.0829,
      "fr": 0.005,
      "ls": 1.15610176800345,
      "oi": 6.84002403894,
      "oiChg": -0.8339352752401228,
      "longs": 53.620000000000005,
      "shorts": 46.379999999999995
    },
    "APT": {
      "price": 0.6011,
      "change": 5.7343,
      "fr": 0.01,
      "ls": 2.802281368821293,
      "oi": 15.841033765195998,
      "oiChg": 1.4340820284267817,
      "longs": 73.7,
      "shorts": 26.3
    },
    "JTO": {
      "price": 0.7951,
      "change": 2.7393,
      "fr": 0.005,
      "ls": 1.15610176800345,
      "oi": 9.089136035760001,
      "oiChg": 0.9423491930819828,
      "longs": 53.620000000000005,
      "shorts": 46.379999999999995
    },
    "XMR": {
      "price": 307.28,
      "change": 0.2414,
      "fr": 0.01,
      "ls": 2.0826140567200984,
      "oi": 21.7479540232,
      "oiChg": -0.2088578985170351,
      "longs": 67.56,
      "shorts": 32.440000000000005
    },
    "MNT": {
      "price": 0.4202,
      "change": 0.9125,
      "fr": 0.01,
      "ls": 4.344735435595938,
      "oi": 22.90079898392,
      "oiChg": -0.45180831055934645,
      "longs": 81.28999999999999,
      "shorts": 18.709999999999997
    },
    "JUP": {
      "price": 0.23488,
      "change": 13.0154,
      "fr": 0.005,
      "ls": 1.4473813020068527,
      "oi": 11.20637987968,
      "oiChg": -0.4581159151060373,
      "longs": 59.14,
      "shorts": 40.86
    },
    "PUMP": {
      "price": 0,
      "change": 0,
      "fr": 0,
      "ls": 1,
      "oi": 0,
      "oiChg": 0,
      "longs": 50,
      "shorts": 50
    },
    "ETC": {
      "price": 7.024,
      "change": 0.6446999999999999,
      "fr": -0.0057599999999999995,
      "ls": 1.9708853238265003,
      "oi": 7.294508287999999,
      "oiChg": 0.23536942459867963,
      "longs": 66.34,
      "shorts": 33.660000000000004
    },
    "FIL": {
      "price": 0.7485,
      "change": 4.5391,
      "fr": 0.01,
      "ls": 2.102699348433137,
      "oi": 8.775321036300001,
      "oiChg": -0.16731008654054536,
      "longs": 67.77,
      "shorts": 32.23
    },
    "ARB": {
      "price": 0.07842,
      "change": 5.1206000000000005,
      "fr": 0.003405,
      "ls": 2.8255547054322876,
      "oi": 13.357400684256003,
      "oiChg": -1.4647005054205375,
      "longs": 73.86,
      "shorts": 26.14
    },
    "CAKE": {
      "price": 1.332,
      "change": 1.8582,
      "fr": 0.005,
      "ls": 1.5207965717166623,
      "oi": 2.04595866,
      "oiChg": -0.4821933031213054,
      "longs": 60.33,
      "shorts": 39.67
    },
    "PYTH": {
      "price": 0.03946,
      "change": 0.22859999999999997,
      "fr": 0.004456,
      "ls": 2.4048348655090233,
      "oi": 4.41809738808,
      "oiChg": 1.3281300029905043,
      "longs": 70.63000000000001,
      "shorts": 29.37
    },
    "VET": {
      "price": 0.004585,
      "change": 4.6564000000000005,
      "fr": 0.01,
      "ls": 2.4188034188034186,
      "oi": 2.864235052665,
      "oiChg": -0.4457258730533557,
      "longs": 70.75,
      "shorts": 29.25
    },
    "ICP": {
      "price": 2.196,
      "change": 3.5360000000000005,
      "fr": 0.000505,
      "ls": 2.6390101892285296,
      "oi": 14.684437231200002,
      "oiChg": -2.0083525802470565,
      "longs": 72.52,
      "shorts": 27.48
    },
    "TIA": {
      "price": 0.3735,
      "change": 2.3568,
      "fr": -0.012929,
      "ls": 2.088326127239037,
      "oi": 7.823603132100001,
      "oiChg": -0.1954925333354209,
      "longs": 67.62,
      "shorts": 32.379999999999995
    },
    "FET": {
      "price": 0,
      "change": 0,
      "fr": 0,
      "ls": 1,
      "oi": 0,
      "oiChg": 0,
      "longs": 50,
      "shorts": 50
    },
    "HBAR": {
      "price": 0.07169,
      "change": 1.8901999999999999,
      "fr": 0.01,
      "ls": 2.6886757654002214,
      "oi": 17.82752523138,
      "oiChg": -0.3693999565235532,
      "longs": 72.89,
      "shorts": 27.11
    },
    "ZEC": {
      "price": 415.13,
      "change": 4.4089,
      "fr": 0.01,
      "ls": 1.2794620469569182,
      "oi": 51.5850750198,
      "oiChg": 1.5251179411577813,
      "longs": 56.13,
      "shorts": 43.87
    },
    "DASH": {
      "price": 33.25,
      "change": 1.2176,
      "fr": 0.01,
      "ls": 2.1298904538341157,
      "oi": 4.41683424,
      "oiChg": 4.674020115593069,
      "longs": 68.05,
      "shorts": 31.95
    },
    "SEI": {
      "price": 0.04849,
      "change": 0.5182,
      "fr": -0.000569,
      "ls": 2.648303538854433,
      "oi": 9.025005447379998,
      "oiChg": 0.8278644304969147,
      "longs": 72.59,
      "shorts": 27.41
    },
    "TAO": {
      "price": 205.23,
      "change": 1.3081,
      "fr": -0.001601,
      "ls": 2.8971161340607945,
      "oi": 26.690769801720002,
      "oiChg": -0.6820896293127663,
      "longs": 74.33999999999999,
      "shorts": 25.66
    }
  },
  "calendar": [
    {
      "id": "fred-CPIAUCSL-2026-07-10",
      "name": "US CPI m/m",
      "cat": "MACRO",
      "impact": "high",
      "date": "2026-07-10T13:30:00Z",
      "desc": "US CPI m/m — FRED API (Consumer Price Index for All Urban Consumers: All Items in U.S. City Average)",
      "fredId": "CPIAUCSL",
      "calcMode": "mom",
      "hasHistory": true,
      "reading": {
        "actual": 0.47,
        "previous": 0.64,
        "trend": {
          "direction": "falling",
          "label": "📉 Falling 2nd month",
          "months": 2
        }
      },
      "hist": [
        {
          "date": "2026-01-01",
          "value": 0.17,
          "calcMode": "mom",
          "btcChange": 2.02
        },
        {
          "date": "2026-02-01",
          "value": 0.27,
          "calcMode": "mom",
          "btcChange": -1.58
        },
        {
          "date": "2026-03-01",
          "value": 0.87,
          "calcMode": "mom",
          "btcChange": 3.88
        },
        {
          "date": "2026-04-01",
          "value": 0.64,
          "calcMode": "mom",
          "btcChange": -1.69
        },
        {
          "date": "2026-05-01",
          "value": 0.47,
          "calcMode": "mom",
          "btcChange": 0.44
        }
      ]
    },
    {
      "id": "fred-CPIAUCSL_YOY-2026-07-10",
      "name": "US CPI y/y",
      "cat": "MACRO",
      "impact": "high",
      "date": "2026-07-10T13:30:00Z",
      "desc": "US CPI y/y — FRED API (Consumer Price Index for All Urban Consumers: All Items in U.S. City Average)",
      "fredId": "CPIAUCSL",
      "calcMode": "yoy",
      "hasHistory": true,
      "reading": {
        "actual": 4.27,
        "previous": 3.95,
        "trend": {
          "direction": "rising",
          "label": "📈 Rising 2nd month",
          "months": 2
        }
      },
      "hist": [
        {
          "date": "2026-01-01",
          "value": 2.83,
          "calcMode": "yoy",
          "btcChange": 2.02
        },
        {
          "date": "2026-02-01",
          "value": 2.66,
          "calcMode": "yoy",
          "btcChange": -1.58
        },
        {
          "date": "2026-03-01",
          "value": 3.32,
          "calcMode": "yoy",
          "btcChange": 3.88
        },
        {
          "date": "2026-04-01",
          "value": 3.95,
          "calcMode": "yoy",
          "btcChange": -1.69
        },
        {
          "date": "2026-05-01",
          "value": 4.27,
          "calcMode": "yoy",
          "btcChange": 0.44
        }
      ]
    },
    {
      "id": "fred-CPILFESL-2026-07-10",
      "name": "US Core CPI m/m",
      "cat": "MACRO",
      "impact": "high",
      "date": "2026-07-10T13:30:00Z",
      "desc": "US Core CPI m/m — FRED API (Consumer Price Index for All Urban Consumers: All Items Less Food and Energy in U.S. City Average)",
      "fredId": "CPILFESL",
      "calcMode": "mom",
      "hasHistory": true,
      "reading": {
        "actual": 0.21,
        "previous": 0.38,
        "trend": {
          "direction": "falling",
          "label": "📉 Falling",
          "months": 1
        }
      },
      "hist": [
        {
          "date": "2026-01-01",
          "value": 0.3,
          "calcMode": "mom",
          "btcChange": 2.02
        },
        {
          "date": "2026-02-01",
          "value": 0.22,
          "calcMode": "mom",
          "btcChange": -1.58
        },
        {
          "date": "2026-03-01",
          "value": 0.2,
          "calcMode": "mom",
          "btcChange": 3.88
        },
        {
          "date": "2026-04-01",
          "value": 0.38,
          "calcMode": "mom",
          "btcChange": -1.69
        },
        {
          "date": "2026-05-01",
          "value": 0.21,
          "calcMode": "mom",
          "btcChange": 0.44
        }
      ]
    },
    {
      "id": "fred-CPILFESL_YOY-2026-07-10",
      "name": "US Core CPI y/y",
      "cat": "MACRO",
      "impact": "high",
      "date": "2026-07-10T13:30:00Z",
      "desc": "US Core CPI y/y — FRED API (Consumer Price Index for All Urban Consumers: All Items Less Food and Energy in U.S. City Average)",
      "fredId": "CPILFESL",
      "calcMode": "yoy",
      "hasHistory": true,
      "reading": {
        "actual": 2.96,
        "previous": 2.99,
        "trend": {
          "direction": "flat",
          "label": "➡️ Flat",
          "months": 1
        }
      },
      "hist": [
        {
          "date": "2026-01-01",
          "value": 2.95,
          "calcMode": "yoy",
          "btcChange": 2.02
        },
        {
          "date": "2026-02-01",
          "value": 2.73,
          "calcMode": "yoy",
          "btcChange": -1.58
        },
        {
          "date": "2026-03-01",
          "value": 2.67,
          "calcMode": "yoy",
          "btcChange": 3.88
        },
        {
          "date": "2026-04-01",
          "value": 2.99,
          "calcMode": "yoy",
          "btcChange": -1.69
        },
        {
          "date": "2026-05-01",
          "value": 2.96,
          "calcMode": "yoy",
          "btcChange": 0.44
        }
      ]
    },
    {
      "id": "fred-FEDFUNDS-2026-07-01",
      "name": "Fed Rate Decision",
      "cat": "MACRO",
      "impact": "high",
      "date": "2026-07-01T13:30:00Z",
      "desc": "Fed Rate Decision — FRED API (Federal Funds Effective Rate)",
      "fredId": "FEDFUNDS",
      "calcMode": "level",
      "hasHistory": true,
      "reading": {
        "actual": 3.63,
        "previous": 3.64,
        "trend": {
          "direction": "flat",
          "label": "➡️ Flat",
          "months": 1
        }
      },
      "hist": [
        {
          "date": "2026-01-01",
          "value": 3.64,
          "calcMode": "level",
          "btcChange": 2.02
        },
        {
          "date": "2026-02-01",
          "value": 3.64,
          "calcMode": "level",
          "btcChange": -1.58
        },
        {
          "date": "2026-03-01",
          "value": 3.64,
          "calcMode": "level",
          "btcChange": 3.88
        },
        {
          "date": "2026-04-01",
          "value": 3.64,
          "calcMode": "level",
          "btcChange": -1.69
        },
        {
          "date": "2026-05-01",
          "value": 3.63,
          "calcMode": "level",
          "btcChange": 0.44
        }
      ]
    },
    {
      "id": "fred-GDP-2026-09-13",
      "name": "US GDP Release",
      "cat": "MACRO",
      "impact": "high",
      "date": "2026-09-13T13:30:00Z",
      "desc": "US GDP Release — FRED API (Gross Domestic Product)",
      "fredId": "GDP",
      "calcMode": "qoq",
      "hasHistory": true,
      "reading": {
        "actual": 1.41,
        "previous": 1.04,
        "trend": {
          "direction": "rising",
          "label": "📈 Rising",
          "months": 1
        }
      },
      "hist": [
        {
          "date": "2025-01-01",
          "value": 0.73,
          "calcMode": "qoq",
          "btcChange": 3.78
        },
        {
          "date": "2025-04-01",
          "value": 1.48,
          "calcMode": "qoq",
          "btcChange": -2.3
        },
        {
          "date": "2025-07-01",
          "value": 2.01,
          "calcMode": "qoq",
          "btcChange": 3.7
        },
        {
          "date": "2025-10-01",
          "value": 1.04,
          "calcMode": "qoq",
          "btcChange": 3.06
        },
        {
          "date": "2026-01-01",
          "value": 1.41,
          "calcMode": "qoq",
          "btcChange": 2.02
        }
      ]
    }
  ],
  "fearGreed": {
    "value": 11,
    "label": "Extreme Fear"
  },
  "coinOrder": [
    "BTC",
    "ETH",
    "SOL",
    "XRP",
    "BNB",
    "DOGE",
    "ADA",
    "AVAX",
    "LINK",
    "DOT",
    "MATIC",
    "NEAR",
    "SUI",
    "LTC",
    "ATOM",
    "UNI",
    "AAVE",
    "TRX",
    "HYPE",
    "ZEC",
    "XLM",
    "XMR",
    "BCH",
    "HBAR",
    "SHIB",
    "CRO",
    "TAO",
    "ONDO",
    "WLD",
    "MNT",
    "ICP",
    "ETC",
    "PEPE",
    "KAS",
    "RENDER",
    "QNT",
    "ALGO",
    "JUP",
    "ENA",
    "PUMP",
    "FIL",
    "ARB",
    "APT",
    "INJ",
    "CAKE",
    "DASH",
    "VET",
    "BONK",
    "JTO",
    "SEI",
    "TIA",
    "PYTH",
    "FET"
  ]
}